setup.py
CydraGitServerGlue.egg-info/PKG-INFO
CydraGitServerGlue.egg-info/SOURCES.txt
CydraGitServerGlue.egg-info/dependency_links.txt
CydraGitServerGlue.egg-info/entry_points.txt
CydraGitServerGlue.egg-info/namespace_packages.txt
CydraGitServerGlue.egg-info/requires.txt
CydraGitServerGlue.egg-info/top_level.txt
cydraplugins/__init__.py
cydraplugins/gitserverglue/__init__.py